dax/BidsToXnat.py
dax/XnatToBids.py
dax/XnatUtils.py
dax/__init__.py
dax/assessor_utils.py
dax/bin.py
dax/cluster.py
dax/dax_manager.py
dax/dax_settings.py
dax/dax_tools_utils.py
dax/errors.py
dax/git_revision.py
dax/launcher.py
dax/lockfiles.py
dax/log.py
dax/modules.py
dax/processor_graph.py
dax/processor_parser.py
dax/processors.py
dax/processors_v3.py
dax/suppdf.py
dax/task.py
dax/test_suppdf.py
dax/utilities.py
dax/validate.py
dax/version.py
dax/xnat_tools_utils.py
dax/yaml_doc.py
dax/rcq/__init__.py
dax/rcq/analysislauncher.py
dax/rcq/projectinfo.py
dax/rcq/taskbuilder.py
dax/rcq/tasklauncher.py
dax/rcq/taskqueue.py
dax/rcq/trialbuilder.py
dax/schema/processor.yaml
dax/schema/project_processor.yaml
dax/schema/subject_processor.yaml
dax/tests/__init__.py
dax/tests/common_session_tools.py
dax/tests/component_test_build.py
dax/tests/component_test_xnatutils.py
dax/tests/test_dax.py
dax/tests/unit_test_assessor_wrapper.py
dax/tests/unit_test_autoprocessor.py
dax/tests/unit_test_common_processor_yamls.py
dax/tests/unit_test_common_pyxnat_objects.py
dax/tests/unit_test_entity_common.py
dax/tests/unit_test_processor_graph.py
dax/tests/unit_test_processor_parser.py
dax/tests/unit_test_utilities.py
dax/tests/unit_test_xnatinterface.py
dax/tests/unit_test_xnatutils.py
dax-2.17.0.data/scripts/BIDSMapping
dax-2.17.0.data/scripts/Redcapreport
dax-2.17.0.data/scripts/XnatAssessorFile
dax-2.17.0.data/scripts/XnatBOND
dax-2.17.0.data/scripts/XnatChangePrearchiveProject
dax-2.17.0.data/scripts/XnatCheckLogin
dax-2.17.0.data/scripts/XnatDemographic
dax-2.17.0.data/scripts/XnatDetailedReport.m
dax-2.17.0.data/scripts/XnatNDAR
dax-2.17.0.data/scripts/XnatRandomSessionList
dax-2.17.0.data/scripts/XnatRepushExamcards.py
dax-2.17.0.data/scripts/XnatShareSession
dax-2.17.0.data/scripts/XnatSwitchProcessStatus
dax-2.17.0.data/scripts/Xnatcheck
dax-2.17.0.data/scripts/Xnatdl
dax-2.17.0.data/scripts/Xnatdownload
dax-2.17.0.data/scripts/Xnatinfo
dax-2.17.0.data/scripts/Xnatmirror
dax-2.17.0.dist-info/LICENSE
dax-2.17.0.dist-info/METADATA
dax-2.17.0.dist-info/WHEEL
dax-2.17.0.dist-info/top_level.txt
dax-2.17.0.dist-info/zip-safe
dax-2.17.0.dist-info/RECORD
