Metadata-Version: 2.1
Name: dax
Version: 2.17.0
Summary: Distributed Automation for XNAT
Home-page: http://github.com/VUIIS/dax
Download-URL: http://github.com/VUIIS/dax
Author: VUIIS CCI
Author-email: vuiis-cci@googlegroups.com
Maintainer: VUIIS CCI
Maintainer-email: vuiis-cci@googlegroups.com
License: MIT
Platform: MacOs
Platform: Linux
Classifier: Development Status :: 5 - Production/Stable
Classifier: Environment :: Console
Classifier: Intended Audience :: Science/Research
Classifier: Operating System :: MacOS :: MacOS X
Classifier: Operating System :: POSIX
Classifier: Operating System :: POSIX :: Linux
Classifier: Operating System :: Unix
Classifier: Programming Language :: Python :: 3.7
Classifier: Topic :: Scientific/Engineering
Classifier: Topic :: Scientific/Engineering :: Information Analysis
Requires-Python: ~=3.6
License-File: LICENSE
Requires-Dist: pyxnat >=1.1.0.2
Requires-Dist: pyyaml
Requires-Dist: pycap
Requires-Dist: pandas
Requires-Dist: fpdf2
Requires-Dist: PyPDF2
Requires-Dist: yamale
Provides-Extra: bids
Requires-Dist: cubids-bond-fork ; extra == 'bids'
Requires-Dist: nibabel ; extra == 'bids'
Provides-Extra: docs
Requires-Dist: Sphinx >=4 ; extra == 'docs'
